<?xml version="1.0" encoding="UTF-8"?>
<!DOCTYPE why3session PUBLIC "-//Why3//proof session v5//EN"
"https://www.why3.org/why3session.dtd">
<why3session shape_version="6">
<prover id="1" name="Alt-Ergo" version="2.5.2" timelimit="1" steplimit="0" memlimit="1000"/>
<file format="ocaml">
<path name=".."/><path name="find.ml"/>
<theory name="Find">
 <goal name="Make.find&#39;vc" expl="VC for find" proved="true">
 <transf name="split_vc" proved="true" >
  <goal name="find&#39;vc.0" expl="loop invariant init" proved="true">
  <proof prover="1"><result status="valid" time="0.010000" steps="16"/></proof>
  </goal>
  <goal name="find&#39;vc.1" expl="index in array bounds" proved="true">
  <proof prover="1"><result status="valid" time="0.010000" steps="18"/></proof>
  </goal>
  <goal name="find&#39;vc.2" expl="postcondition" proved="true">
  <proof prover="1"><result status="valid" time="0.010000" steps="20"/></proof>
  </goal>
  <goal name="find&#39;vc.3" expl="loop invariant preservation" proved="true">
  <proof prover="1"><result status="valid" time="0.010000" steps="33"/></proof>
  </goal>
  <goal name="find&#39;vc.4" expl="exceptional postcondition" proved="true">
  <proof prover="1"><result status="valid" time="0.010000" steps="20"/></proof>
  </goal>
  <goal name="find&#39;vc.5" expl="exceptional postcondition" proved="true">
  <proof prover="1"><result status="valid" time="0.000000" steps="16"/></proof>
  </goal>
 </transf>
 </goal>
 <goal name="MakeList.mem&#39;vc" expl="VC for mem">
 </goal>
</theory>
</file>
</why3session>
